README.md
setup.cfg
setup.py
maxwell/__init__.py
maxwell_api_client.egg-info/PKG-INFO
maxwell_api_client.egg-info/SOURCES.txt
maxwell_api_client.egg-info/dependency_links.txt
maxwell_api_client.egg-info/requires.txt
maxwell_api_client.egg-info/top_level.txt