Metadata-Version: 1.0
Name: maxwell-api-client
Version: 0.1.0
Summary: Maxwell API Client
Home-page: https://bitbucket.org/maxwellai/maxwell-api-client
Author: Bas Wind
Author-email: mailtobwind+mac@gmail.com
License: UNKNOWN
Platform: UNKNOWN
